{ 
  "Default Floral Ecotopes": [
	{ "//": "forests" },
	{ "name": "Conifers",	"id": 1,	"order": 1,
	  "class": "Tree",
	  "alt":   { "min": 1500, "max": 2500 },
	  "temp":  { "max": 25 },
	  "rain":  { "min": 30,  "max": 90 },
	  "vigor": 32,
	   "bid": "tapered",
	  "color": [0,102,51]
	},
	{ "name": "Broadleaf",	 "id": 2,	"order": 1,
	  "class": "Tree",
	  "alt":   { "min": 500, "max": 2000 },
	  "temp":  { "min": 0,   "max": 30 },
	  "rain":  { "min": 75,  "max": 120 },
	  "vigor": 32,
	   "bid": "tapered",
	  "color": [128,255,0]
	},
	{ "name": "Jungle",	"id": 3,	"order": 1,
	  "class": "Tree",
	  "alt":   { "min": 0,  "max": 1000 },
	  "temp":  { "min": 15 },
	  "rain":  { "min": 100 },
	  "vigor": 32,
	  "bid": "tapered",
	  "color": [76,153,0]
	},

	{ "//": "Riperian and Marsh have very limited habitat" },
	{ "name": "Riperian",	"id": 6,	"order": 2,
	  "class": "Brush",	
	  "alt":   { "min": 250, "max": 1500 },
	  "temp":  { "min": 0,  "max": 28 },
	  "rain":  { "min": 75,  "max": 120 },
	  "flux":  { "min": 0.3, "max": 2.0 },
	  "hydro": { "min": 0.1 },
	  "vigor": 32,
	  "bid": "tapered",
	  "color": [178,102,255]
	},
	{ "name": "Marsh",	"id": 13,	"order": 2,
	  "class": "Grass",
	  "alt":   { "min": 0,   "max": 1000 },
	  "temp":  { "min": 0 },
	  "rain":  { "min": 50,  "max": 100 },
	  "depth": { "min": 0.1, "max": 1.0},
	  "slope": { "max": 0.1 },
	  "vigor": 32,
	  "color": [153,255,204]
	},

	{ "//": "more robust brush" },
	{ "name": "Brush",	"id": 7,	"order": 3,
	  "class": "Brush",
	  "alt":   { "min": 0,  "max": 1000 },
	  "rain":  { "min": 25,  "max": 50 },
	  "vigor": 16,
	  "range": "flexible",	"bid": "tapered",
	  "color": [0,153,153]
	},

	{ "//": "more robust grasses" },
	{ "name": "Grassland",	"id": 11,	"order": 4,
	  "class": "Grass",
	  "alt":   { "min": 100,   "max": 1500 },
	  "temp":  { "min": 0,   "max": 20 },
	  "rain":  { "min": 25,  "max": 70 },
	  "slope": { "max": 0.1 },
	  "vigor": 32,
	  "range": "flexible",	"bid": "tapered",
	  "color": [178,255,102]
	},

	{ "//": "barrens go where nothing else can live" },
	{ "name": "Alpine",	"id": 16,
	  "class": "Barren",
	  "alt":   { "min": 2500 },
	  "temp":  { "max": 15 },
	  "vigor": 32,
	  "bid": "tapered",
	  "color": [192,192,192]
	},
	{ "name": "Desert",	"id": 17,
	  "class": "Barren",
	  "temp":  { "min": 15 },
	  "rain":  { "max": 25 },
	  "vigor": 32,
	  "color": [255,204,153]
	}
    ]
}
